localdates
