Metadata-Version: 1.0
Name: django-localdates
Version: 0.2.1
Summary: An addition to django that allows better presentation of date strings in a local way.
Home-page: http://code.google.com/p/django-localdates/
Author: Orestis Markou
Author-email: orestis@orestis.gr
License: UNKNOWN
Platform: UNKNOWN
Classifier: Development Status :: 5 - Production/Stable
Classifier: Environment :: Web Environment
Classifier: Intended Audience :: Developers
Classifier: License :: OSI Approved :: BSD License
Classifier: Operating System :: OS Independent
Classifier: Programming Language :: Python
Classifier: Topic :: Utilities
